pccora/__init__.py
pccora/pccora.py
pccora/version.py
pccora-0.1.dist-info/DESCRIPTION.rst
pccora-0.1.dist-info/METADATA
pccora-0.1.dist-info/RECORD
pccora-0.1.dist-info/WHEEL
pccora-0.1.dist-info/metadata.json
pccora-0.1.dist-info/top_level.txt
