Metadata-Version: 2.0
Name: pccora
Version: 0.1
Summary: PC-CORA sounding data files parser for Python
Home-page: http://github.com/niwa/pccora
Author: Bruno P. Kinoshita
Author-email: brunodepaulak@yahoo.com.br
License: MIT
Keywords: sounding file,radiosonde,vaisala,pccora
Platform: UNKNOWN
